{
"type": "FeatureCollection",
"name": "station_data_sexy_map",
"crs": { "type": "name", "properties": { "name": "urn:ogc:def:crs:OGC:1.3:CRS84" } },
"features": [
{ "type": "Feature", "properties": { "Lon": -63.39249998, "Lat": -51.9125, "Station": 364 }, "geometry": { "type": "Point", "coordinates": [ -63.39249998, -51.9125 ] } },
{ "type": "Feature", "properties": { "Lon": -63.06333333, "Lat": -51.88349997, "Station": 366 }, "geometry": { "type": "Point", "coordinates": [ -63.06333333, -51.88349997 ] } },
{ "type": "Feature", "properties": { "Lon": -63.003, "Lat": -51.27716665, "Station": 389 }, "geometry": { "type": "Point", "coordinates": [ -63.003, -51.27716665 ] } },
{ "type": "Feature", "properties": { "Lon": -62.64449997, "Lat": -51.81383337, "Station": 368 }, "geometry": { "type": "Point", "coordinates": [ -62.64449997, -51.81383337 ] } },
{ "type": "Feature", "properties": { "Lon": -61.76733335, "Lat": -50.5905, "Station": 416 }, "geometry": { "type": "Point", "coordinates": [ -61.76733335, -50.5905 ] } },
{ "type": "Feature", "properties": { "Lon": -61.74899998, "Lat": -51.40833333, "Station": 395 }, "geometry": { "type": "Point", "coordinates": [ -61.74899998, -51.40833333 ] } },
{ "type": "Feature", "properties": { "Lon": -61.43800002, "Lat": -50.13233333, "Station": 436 }, "geometry": { "type": "Point", "coordinates": [ -61.43800002, -50.13233333 ] } },
{ "type": "Feature", "properties": { "Lon": -61.42150002, "Lat": -50.389, "Station": 433 }, "geometry": { "type": "Point", "coordinates": [ -61.42150002, -50.389 ] } },
{ "type": "Feature", "properties": { "Lon": -60.9205, "Lat": -49.36966667, "Station": 456 }, "geometry": { "type": "Point", "coordinates": [ -60.9205, -49.36966667 ] } },
{ "type": "Feature", "properties": { "Lon": -60.59833337, "Lat": -45.9, "Station": 705 }, "geometry": { "type": "Point", "coordinates": [ -60.59833337, -45.9 ] } },
{ "type": "Feature", "properties": { "Lon": -60.28149998, "Lat": -49.496, "Station": 461 }, "geometry": { "type": "Point", "coordinates": [ -60.28149998, -49.496 ] } },
{ "type": "Feature", "properties": { "Lon": -59.56666667, "Lat": -52.98333333, "Station": 629 }, "geometry": { "type": "Point", "coordinates": [ -59.56666667, -52.98333333 ] } },
{ "type": "Feature", "properties": { "Lon": -59.14183333, "Lat": -50.3055, "Station": 486 }, "geometry": { "type": "Point", "coordinates": [ -59.14183333, -50.3055 ] } },
{ "type": "Feature", "properties": { "Lon": -58.76666667, "Lat": -50.29616667, "Station": 488 }, "geometry": { "type": "Point", "coordinates": [ -58.76666667, -50.29616667 ] } }
]
}
